skeleton_methods/__init__.py
skeleton_methods/clustering.py
skeleton_methods/regression.py
skeleton_methods/skeleton.py
skeleton_methods/utils.py
skeleton_methods-0.0.4.dist-info/LICENSE
skeleton_methods-0.0.4.dist-info/METADATA
skeleton_methods-0.0.4.dist-info/WHEEL
skeleton_methods-0.0.4.dist-info/top_level.txt
skeleton_methods-0.0.4.dist-info/RECORD
