Metadata-Version: 2.1
Name: skeleton-methods
Version: 0.0.4
Summary: Skeleton-Based Methods for Clustering and Regression on Underlying Manifolds
Home-page: https://github.com/zhangyk8/skeleton-methods
Author: Zeyu Wei, Yikun Zhang
Author-email: zwei5@uw.edu, yikunzhang@foxmail.com
Classifier: Programming Language :: Python :: 3
Classifier: License :: OSI Approved :: MIT License
Classifier: Operating System :: OS Independent
Requires-Python: >=3.6
License-File: LICENSE
Requires-Dist: numpy
Requires-Dist: scipy
Requires-Dist: scikit-learn
Requires-Dist: igraph
